examples/__init__.py
examples/notebook.ipynb
examples/notebook.py
examples/script.py
aignostics/CLAUDE.md
aignostics/__init__.py
aignostics/cli.py
aignostics/constants.py
aignostics/application/CLAUDE.md
aignostics/application/__init__.py
aignostics/application/_cli.py
aignostics/application/_download.py
aignostics/application/_models.py
aignostics/application/_service.py
aignostics/application/_settings.py
aignostics/application/_utils.py
aignostics/application/_gui/_frame.py
aignostics/application/_gui/_page_application_describe.py
aignostics/application/_gui/_page_application_run_describe.py
aignostics/application/_gui/_page_builder.py
aignostics/application/_gui/_page_index.py
aignostics/application/_gui/_utils.py
aignostics/application/_gui/assets/.gitignore
aignostics/application/_gui/assets/canceled.lottie
aignostics/application/_gui/assets/done.lottie
aignostics/application/_gui/assets/empty.lottie
aignostics/application/_gui/assets/error.lottie
aignostics/application/_gui/assets/error_alt.lottie
aignostics/application/_gui/assets/home-card-1.png
aignostics/application/_gui/assets/home-card-2.png
aignostics/application/_gui/assets/home-card-3.png
aignostics/application/_gui/assets/home-card-4.png
aignostics/application/_gui/assets/home-card-5.png
aignostics/application/_gui/assets/image-not-found.png
aignostics/application/_gui/assets/pending.lottie
aignostics/application/_gui/assets/processing.lottie
aignostics/application/_gui/assets/ruo.png
aignostics/application/_gui/assets/ruo.svg
aignostics/bucket/CLAUDE.md
aignostics/bucket/__init__.py
aignostics/bucket/_cli.py
aignostics/bucket/_gui.py
aignostics/bucket/_service.py
aignostics/bucket/_settings.py
aignostics/bucket/assets/Google-Cloud-logo.png
aignostics/bucket/assets/Google-Cloud-logo.svg
aignostics/dataset/CLAUDE.md
aignostics/dataset/__init__.py
aignostics/dataset/_cli.py
aignostics/dataset/_gui.py
aignostics/dataset/_service.py
aignostics/dataset/assets/NIH-IDC-logo.svg
aignostics/gui/CLAUDE.md
aignostics-1.0.3.dist-info/METADATA
aignostics-1.0.3.dist-info/WHEEL
aignostics-1.0.3.dist-info/entry_points.txt
aignostics-1.0.3.dist-info/licenses/LICENSE
aignostics-1.0.3.dist-info/RECORD
