Metadata-Version: 2.4
Name: aignostics
Version: 1.0.3
Summary: 🔬 Python SDK providing access to the Aignostics Platform. Includes Aignostics Launchpad (Desktop Application), Aignostics CLI (Command-Line Interface), example notebooks, and Aignostics Client Library.
Project-URL: Homepage, https://aignostics.readthedocs.io/en/latest/
Project-URL: Documentation, https://aignostics.readthedocs.io/en/latest/
Project-URL: Source, https://github.com/aignostics/python-sdk
Project-URL: Changelog, https://github.com/aignostics/python-sdk/releases
Project-URL: Issues, https://github.com/aignostics/python-sdk/issues
Author-email: Helmut Hoffer von Ankershoffen <helmut@aignostics.com>, Andreas Kunft <andreas@aignostics.com>
License: MIT License
License-File: LICENSE
Keywords: act,aignostics,atlas,codecov,copier,cyclonedx,detect-secrets,devcontainer,dicom,digital-pathology,docker,git-cliff,image-data-commons,jupyter,machine-learning,marimo,medical-imaging,mypy,nicegui,nox,oe-python-template,openslide,pip-audit,pip-licenses,pre-commit,pydantic,pydicom,pypi,pytest,python,qupath,readthedocs,ruff,sonarcloud,sonarqube,sphinx,typer,uv,whole-slide-imaging
Classifier: Development Status :: 3 - Alpha
Classifier: Framework :: Pydantic
Classifier: Framework :: Pytest
Classifier: Intended Audience :: Developers
Classifier: Intended Audience :: End Users/Desktop
Classifier: License :: OSI Approved :: MIT License
Classifier: Natural Language :: English
Classifier: Operating System :: MacOS :: MacOS X
Classifier: Operating System :: Microsoft :: Windows
Classifier: Operating System :: POSIX :: Linux
Classifier: Programming Language :: Python
Classifier: Programming Language :: Python :: 3
Classifier: Programming Language :: Python :: 3.11
Classifier: Programming Language :: Python :: 3.12
Classifier: Programming Language :: Python :: 3.13
Classifier: Programming Language :: Python :: 3.14
Classifier: Typing :: Typed
Requires-Python: <3.15,>=3.11
Requires-Dist: aiohttp>=3.13.3
Requires-Dist: boto3<2,>=1.42.4
Requires-Dist: certifi>=2025.11.12
Requires-Dist: crc32c<3,>=2.8
Requires-Dist: defusedxml>=0.7.1
Requires-Dist: dicom-validator<1,>=0.7.3
Requires-Dist: dicomweb-client[gcp]<1,>=0.59.3
Requires-Dist: duckdb<=2,>=1.4.2
Requires-Dist: fastapi[all,standard]>=0.123.10
Requires-Dist: fastparquet<2026.0.0,>=2025.12.0; python_version < '3.14'
Requires-Dist: filelock>=3.20.1
Requires-Dist: google-cloud-storage<4,>=3.6.0
Requires-Dist: h11>=0.16.0
Requires-Dist: highdicom<1,>=0.26.1; python_version < '3.14'
Requires-Dist: html-sanitizer<3,>=2.6.0
Requires-Dist: httpx<1,>=0.28.1
Requires-Dist: humanize<5,>=4.14.0
Requires-Dist: idc-index-data==23.2.7
Requires-Dist: ijson<4,>=3.4.0.post0
Requires-Dist: jsf<1,>=0.11.2
Requires-Dist: jsonschema[format-nongpl]<5,>=4.25.1
Requires-Dist: loguru<1,>=0.7.3
Requires-Dist: lxml>=6.0.2
Requires-Dist: marshmallow>=3.26.2
Requires-Dist: nicegui[native]<4,>=3.5.0
Requires-Dist: openslide-bin<5,>=4.0.0.10
Requires-Dist: openslide-python<2,>=1.4.3
Requires-Dist: packaging<26,>=25.0
Requires-Dist: pandas<3,>=2.3.3
Requires-Dist: pillow>=11.3.0
Requires-Dist: platformdirs<5,>=4.3.2
Requires-Dist: platformdirs<5,>=4.5.1
Requires-Dist: procrastinate>=3.5.3
Requires-Dist: psutil<8,>=7.1.3
Requires-Dist: pyarrow<23,>=22.0.0; python_version >= '3.14'
Requires-Dist: pydantic-settings<3,>=2.12.0
Requires-Dist: pyjwt[crypto]<3,>=2.10.1
Requires-Dist: python-dateutil<3,>=2.9.0.post0
Requires-Dist: pywin32<312,>=311; sys_platform == 'win32'
Requires-Dist: pyyaml<7,>=6.0.3
Requires-Dist: requests-oauthlib<3,>=2.0.0
Requires-Dist: requests<3,>=2.32.5
Requires-Dist: rfc3987; sys_platform == 'never'
Requires-Dist: s5cmd<1,>=0.3.3
Requires-Dist: semver<4,>=3.0.4
Requires-Dist: sentry-sdk<3,>=2.47.0
Requires-Dist: shapely<3,>=2.1.2
Requires-Dist: starlette>=0.47.2
Requires-Dist: starlette>=0.49.1
Requires-Dist: tenacity<10,>=9.1.2
Requires-Dist: tornado>=6.5.0
Requires-Dist: tqdm<5,>=4.67.1
Requires-Dist: truststore<1,>=0.10.4
Requires-Dist: typer<1,>=0.20.0
Requires-Dist: uptime<4,>=3.0.1
Requires-Dist: urllib3<3,>=2.6.3
Requires-Dist: urllib3>=2.5.0
Requires-Dist: wsidicom<1,>=0.28.1
Provides-Extra: jupyter
Requires-Dist: jupyter-core>=5.8.1; extra == 'jupyter'
Requires-Dist: jupyter<2,>=1.1.1; extra == 'jupyter'
Requires-Dist: jupyterlab>=4.4.9; extra == 'jupyter'
Provides-Extra: marimo
Requires-Dist: cloudpathlib<1,>=0.23.0; extra == 'marimo'
Requires-Dist: ipython<10,>=9.8.0; extra == 'marimo'
Requires-Dist: marimo<1,>=0.18.4; extra == 'marimo'
Requires-Dist: matplotlib<4,>=3.10.7; extra == 'marimo'
Requires-Dist: shapely<3,>=2.1.0; extra == 'marimo'
Provides-Extra: pyinstaller
Requires-Dist: pyinstaller<7,>=6.14.0; extra == 'pyinstaller'
Provides-Extra: qupath
